{"Name":"cubecart","VersionNodes":[{"Versions":["6.0.4","6.0.3","6.0.2","6.0.1","6.0.0"],"PathHashPairs":[{"Path":"/README.md","Hash":"44aa435932546acd9fb0c51440445c38"}]},{"Versions":["6.2.9","6.2.8","6.2.7","6.2.6","6.2.5","6.2.4","6.2.3","6.2.2","6.2.1","6.2.0","6.1.9","6.1.8","6.1.7","6.1.6","6.1.5","6.1.4","6.1.3","6.1.2","6.1.15","6.1.14","6.1.13","6.1.12","6.1.11","6.1.10","6.1.1","6.1.0","6.0.9","6.0.8","6.0.7","6.0.5","6.0.4","6.0.3","6.0.2","6.0.12","6.0.11","6.0.10","6.0.1","6.0.0"],"PathHashPairs":[{"Path":"/docs/license.txt","Hash":"03f39ea2f1cf67dbb7001bdb3cdffd78"}]},{"Versions":["6.1.0","6.0.9","6.0.8","6.0.7","6.0.5","6.0.4","6.0.3","6.0.2","6.0.12","6.0.11","6.0.10","6.0.1","6.0.0"],"PathHashPairs":[{"Path":"/images/icons/prod_type_1.png","Hash":"6f3686f9ee2f796c759c0e629cf59d6e"}]},{"Versions":["6.0.1","6.0.0"],"PathHashPairs":[{"Path":"/js/common.js","Hash":"e55aaf159a6f0ec141bd32402cba59a7"}]},{"Versions":["6.1.1","6.1.0","6.0.9","6.0.8","6.0.7","6.0.5","6.0.4","6.0.3","6.0.2","6.0.12","6.0.11","6.0.10","6.0.1","6.0.0"],"PathHashPairs":[{"Path":"/js/plugins/jquery.chosen.js","Hash":"ea63447350c993f5f9f7771bb53a0e23"}]},{"Versions":["6.1.9","6.1.8","6.1.7","6.1.6","6.1.5","6.1.4","6.1.3","6.1.2","6.1.13","6.1.12","6.1.11","6.1.10","6.1.1","6.1.0","6.0.9","6.0.8","6.0.7","6.0.5","6.0.4","6.0.3","6.0.2","6.0.12","6.0.11","6.0.10","6.0.1","6.0.0"],"PathHashPairs":[{"Path":"/js/plugins/jquery.colorbox-min.js","Hash":"6834377147c60e2357b3a13653ee0ae5"}]},{"Versions":["6.1.4","6.1.3","6.1.2","6.1.1","6.1.0","6.0.9","6.0.8","6.0.7","6.0.5","6.0.4","6.0.3","6.0.2","6.0.12","6.0.11","6.0.10","6.0.1","6.0.0"],"PathHashPairs":[{"Path":"/js/plugins/jquery.filetree.js","Hash":"f5bb205fb562f415caa849e754ee03a7"}]},{"Versions":["6.0.9","6.0.8","6.0.7","6.0.5","6.0.4","6.0.3","6.0.2","6.0.10","6.0.1","6.0.0"],"PathHashPairs":[{"Path":"/js/plugins/jquery.magnifier.js","Hash":"91f544102de4acaa0e63998f60aa9bb0"}]},{"Versions":["6.1.8","6.1.7","6.1.6","6.1.5","6.1.4","6.1.3","6.1.2","6.1.1","6.1.0","6.0.9","6.0.8","6.0.7","6.0.5","6.0.4","6.0.3","6.0.2","6.0.12","6.0.11","6.0.10","6.0.1","6.0.0"],"PathHashPairs":[{"Path":"/js/styles/images/ui-icons_2e83ff_256x240.png","Hash":"49edfe91577d2fda6915b8c558c25c26"}]},{"Versions":["6.0.9","6.0.8","6.0.7","6.0.5","6.0.4","6.0.3","6.0.2","6.0.12","6.0.11","6.0.10","6.0.1","6.0.0"],"PathHashPairs":[{"Path":"/setup/styles/style.css","Hash":"0f074e9f9197afa1ddb16b2e0f74ab1d"}]},{"Versions":["6.0.8","6.0.7","6.0.5","6.0.4","6.0.3","6.0.2","6.0.1","6.0.0"],"PathHashPairs":[{"Path":"/skins/foundation/js/vendor/jquery.validate.min.js","Hash":"eb12163c46e3c66075e7aac7b2d4f12e"}]},{"Versions":["6.0.9","6.0.8","6.0.7","6.0.12","6.0.11","6.0.10"],"PathHashPairs":[{"Path":"/README.md","Hash":"71b4a203233bd296289b5873a26c95a9"}]},{"Versions":["6.2.9","6.2.8","6.2.7","6.2.6","6.2.5","6.2.4","6.2.3","6.2.2","6.2.1","6.2.0","6.1.9","6.1.8","6.1.7","6.1.6","6.1.5","6.1.4","6.1.3","6.1.2","6.1.15","6.1.14","6.1.13","6.1.12","6.1.11","6.1.10","6.1.1","6.1.0","6.0.9","6.0.8","6.0.7","6.0.5","6.0.4","6.0.3","6.0.2","6.0.12","6.0.11","6.0.10"],"PathHashPairs":[{"Path":"/js/common.js","Hash":"45fbd95220efa70e4c169cd64f68ff05"}]},{"Versions":["6.0.9","6.0.8","6.0.10"],"PathHashPairs":[{"Path":"/skins/foundation/css/cubecart.css","Hash":"895dfd5abdc7e6fd6bb04ddb4ec00e24"}]},{"Versions":["6.0.9","6.0.8","6.0.7","6.0.5","6.0.10"],"PathHashPairs":[{"Path":"/skins/foundation/css/foundation.css","Hash":"551146c7eb13a1d1f64b7be54a1d6d44"}]},{"Versions":["6.1.8","6.1.7","6.1.6","6.1.5","6.1.4","6.1.3","6.1.2","6.1.1","6.1.0","6.0.9","6.0.8","6.0.7","6.0.12","6.0.11","6.0.10"],"PathHashPairs":[{"Path":"/skins/foundation/css/jquery.bxslider.css","Hash":"48feef0f3923cda4051f8991638584d5"}]},{"Versions":["6.2.9","6.2.8","6.2.7","6.2.6","6.2.5","6.2.4","6.2.3","6.2.2","6.2.1","6.2.0","6.1.9","6.1.8","6.1.7","6.1.6","6.1.5","6.1.4","6.1.3","6.1.2","6.1.15","6.1.14","6.1.13","6.1.12","6.1.11","6.1.10","6.1.1","6.1.0","6.0.9","6.0.8","6.0.7","6.0.5","6.0.12","6.0.11","6.0.10"],"PathHashPairs":[{"Path":"/skins/foundation/css/normalize.css","Hash":"eece4dd4942f2406610224731269a89e"}]},{"Versions":["6.2.9","6.2.8","6.2.7","6.2.6","6.2.5","6.2.4","6.2.3","6.2.2","6.2.1","6.1.9","6.1.8","6.1.7","6.1.6","6.1.5","6.1.4","6.1.3","6.1.2","6.1.15","6.1.14","6.1.13","6.1.12","6.1.11","6.1.10","6.1.1","6.1.0","6.0.9","6.0.8","6.0.7","6.0.5","6.0.4","6.0.3","6.0.2","6.0.12","6.0.11","6.0.10"],"PathHashPairs":[{"Path":"/skins/foundation/images/bxslider/bx_loader.gif","Hash":"5ee9e5b505f5831d5772e3349421aba8"}]},{"Versions":["6.2.9","6.2.8","6.2.7","6.2.6","6.2.5","6.2.4","6.2.3","6.2.2","6.2.1","6.2.0","6.1.9","6.1.8","6.1.7","6.1.6","6.1.5","6.1.4","6.1.3","6.1.2","6.1.15","6.1.14","6.1.13","6.1.12","6.1.11","6.1.10","6.1.1","6.0.9","6.0.8","6.0.7","6.0.5","6.0.12","6.0.11","6.0.10"],"PathHashPairs":[{"Path":"/skins/foundation/images/default/logo/default.png","Hash":"0c48b4176a08dbec8ce1a7bd0934e207"}]},{"Versions":["6.0.9","6.0.12","6.0.11","6.0.10"],"PathHashPairs":[{"Path":"/skins/foundation/js/2.cubecart.js","Hash":"c7f01528a8d8df8e99475bef3be228bc"}]},{"Versions":["6.0.9","6.0.11","6.0.10"],"PathHashPairs":[{"Path":"/skins/foundation/js/3.cubecart.validate.js","Hash":"8a48255e42262e5e1c6640ecc37e9cff"}]},{"Versions":["6.1.9","6.1.8","6.1.7","6.1.6","6.1.5","6.1.4","6.1.3","6.1.2","6.1.14","6.1.13","6.1.12","6.1.11","6.1.10","6.1.1","6.1.0","6.0.9","6.0.8","6.0.7","6.0.12","6.0.11","6.0.10"],"PathHashPairs":[{"Path":"/skins/foundation/js/vendor/jquery.bxslider.min.js","Hash":"eba9838e40dbe3665aa3012e8f5f21f7"}]},{"Versions":["6.1.9","6.1.8","6.1.7","6.1.6","6.1.5","6.1.4","6.1.3","6.1.2","6.1.15","6.1.14","6.1.13","6.1.12","6.1.11","6.1.10","6.1.1","6.1.0","6.0.9","6.0.8","6.0.7","6.0.5","6.0.4","6.0.3","6.0.2","6.0.12","6.0.11","6.0.10"],"PathHashPairs":[{"Path":"/skins/foundation/js/vendor/jquery.cookie.min.js","Hash":"35daa67d8838fb86c7d62b6a27346210"}]},{"Versions":["6.1.9","6.1.8","6.1.7","6.1.6","6.1.5","6.1.4","6.1.3","6.1.2","6.1.15","6.1.14","6.1.13","6.1.12","6.1.11","6.1.10","6.1.1","6.1.0","6.0.9","6.0.8","6.0.7","6.0.5","6.0.12","6.0.11","6.0.10"],"PathHashPairs":[{"Path":"/skins/foundation/js/vendor/jquery.js","Hash":"c124f262017d059c60e95fe501f2f3db"}]},{"Versions":["6.1.9","6.1.8","6.1.7","6.1.6","6.1.5","6.1.4","6.1.3","6.1.2","6.1.15","6.1.14","6.1.13","6.1.12","6.1.11","6.1.10","6.1.1","6.1.0","6.0.9","6.0.12","6.0.11","6.0.10"],"PathHashPairs":[{"Path":"/skins/foundation/js/vendor/jquery.validate.min.js","Hash":"5a42d81cfad99eaa724693954a426a9d"}]},{"Versions":["6.2.9","6.2.8","6.2.7","6.2.6","6.2.5","6.2.4","6.2.3","6.2.2","6.2.1","6.2.0","6.1.9","6.1.8","6.1.7","6.1.6","6.1.5","6.1.4","6.1.3","6.1.2","6.1.15","6.1.14","6.1.13","6.1.12","6.1.11","6.1.10","6.1.1","6.1.0","6.0.12","6.0.11"],"PathHashPairs":[{"Path":"/js/plugins/jquery.magnifier.js","Hash":"d32ee3afcb98f3b9dfe306d902342e04"}]},{"Versions":["6.0.12","6.0.11"],"PathHashPairs":[{"Path":"/skins/foundation/css/cubecart.css","Hash":"376b66b15be8841297fd04c69446afb4"}]},{"Versions":["6.2.0","6.1.9","6.1.8","6.1.7","6.1.6","6.1.5","6.1.4","6.1.3","6.1.2","6.1.15","6.1.14","6.1.13","6.1.12","6.1.11","6.1.10","6.1.1","6.1.0","6.0.12","6.0.11"],"PathHashPairs":[{"Path":"/skins/foundation/css/foundation.css","Hash":"f6ad150107e50486b54b2c84967e0b7f"}]},{"Versions":["6.2.2","6.2.1","6.2.0","6.1.9","6.1.8","6.1.7","6.1.6","6.1.5","6.1.4","6.1.3","6.1.2","6.1.15","6.1.14","6.1.13","6.1.12","6.1.11","6.1.10","6.1.1","6.1.0","6.0.12","6.0.11"],"PathHashPairs":[{"Path":"/skins/foundation/images/sprite_flags.png","Hash":"73794afce56d7eb6046e36b077fd8277"}]},{"Versions":["6.0.12"],"PathHashPairs":[{"Path":"/skins/foundation/js/3.cubecart.validate.js","Hash":"73228107b6a74c219e9657d692babdda"}]},{"Versions":["6.0.2"],"PathHashPairs":[{"Path":"/skins/foundation/css/cubecart.css","Hash":"d2b48d3ceb789bd1845cc0f8fa499c86"},{"Path":"/skins/foundation/js/2.cubecart.js","Hash":"da802191b03723a473dc0f427e8d796c"}]},{"Versions":["6.0.4","6.0.3","6.0.2"],"PathHashPairs":[{"Path":"/skins/foundation/css/foundation.css","Hash":"ad2842caf2bd9813861cdb2b02a1677b"}]},{"Versions":["6.0.5","6.0.4","6.0.3","6.0.2"],"PathHashPairs":[{"Path":"/skins/foundation/css/jquery.bxslider.css","Hash":"6a1396f2149410bc798a2052c4a4b3f9"}]},{"Versions":["6.0.4","6.0.3"],"PathHashPairs":[{"Path":"/skins/foundation/css/cubecart.css","Hash":"7239384f6e5221b0963609fdc526972c"}]},{"Versions":["6.0.5"],"PathHashPairs":[{"Path":"/README.md","Hash":"a10870bbd4686634a366472c302cf940"},{"Path":"/skins/foundation/css/cubecart.css","Hash":"ebdcde3411d72e916d11e2150f850fea"},{"Path":"/skins/foundation/js/2.cubecart.js","Hash":"7bd044a283561bfba97bf144bb3e0195"},{"Path":"/skins/foundation/js/vendor/jquery.bxslider.min.js","Hash":"aef5f06d953cd0c9d390ceec61d042a6"}]},{"Versions":["6.0.7"],"PathHashPairs":[{"Path":"/skins/foundation/css/cubecart.css","Hash":"2244ed0e63243ae8e0e9b62b707c3591"},{"Path":"/skins/foundation/js/2.cubecart.js","Hash":"37d151f05ef5be9b0afd3f9b35ccdaef"},{"Path":"/skins/foundation/js/3.cubecart.validate.js","Hash":"74ee6e57c17fee1e02ea4fa63f47e036"}]},{"Versions":["6.0.8"],"PathHashPairs":[{"Path":"/skins/foundation/js/2.cubecart.js","Hash":"a38a9393cbd8d96dd20987528c89d11d"},{"Path":"/skins/foundation/js/3.cubecart.validate.js","Hash":"68a4ff926dc3b03e3cf759ab5f0ae5ff"}]},{"Versions":["6.2.9","6.2.8","6.2.7","6.2.6","6.2.5","6.2.4","6.2.3","6.2.2","6.2.1","6.2.0","6.1.9","6.1.8","6.1.7","6.1.6","6.1.5","6.1.4","6.1.3","6.1.2","6.1.15","6.1.14","6.1.13","6.1.12","6.1.11","6.1.10","6.1.1","6.1.0"],"PathHashPairs":[{"Path":"/setup/images/cubecart-logo.png","Hash":"6132da723ea7e6de4e8746c9afc1f157"}]},{"Versions":["6.2.8","6.2.7","6.2.6","6.2.5","6.2.4","6.2.3","6.2.2","6.2.1","6.2.0","6.1.9","6.1.8","6.1.7","6.1.6","6.1.5","6.1.4","6.1.3","6.1.2","6.1.15","6.1.14","6.1.13","6.1.12","6.1.11","6.1.10","6.1.1","6.1.0"],"PathHashPairs":[{"Path":"/setup/styles/style.css","Hash":"ffcc93b56ef994da32e605a3da7ba0c7"}]},{"Versions":["6.1.3","6.1.2","6.1.1","6.1.0"],"PathHashPairs":[{"Path":"/skins/foundation/css/cubecart.css","Hash":"f49db0015f046e04d58fb55b65f0d01c"}]},{"Versions":["6.2.0","6.1.9","6.1.8","6.1.7","6.1.6","6.1.5","6.1.4","6.1.3","6.1.2","6.1.15","6.1.14","6.1.13","6.1.12","6.1.11","6.1.10","6.1.1","6.1.0"],"PathHashPairs":[{"Path":"/skins/foundation/images/icon-sprites.svg","Hash":"e02c088f3410b2d83e9fdb51d822ff73"}]},{"Versions":["6.1.0"],"PathHashPairs":[{"Path":"/skins/foundation/images/default/logo/default.svg","Hash":"5d9f4fc7c5d607c097735aa38f44dce3"}]},{"Versions":["6.1.9","6.1.8","6.1.7","6.1.6","6.1.5","6.1.4","6.1.3","6.1.2","6.1.15","6.1.14","6.1.13","6.1.12","6.1.11","6.1.10","6.1.1","6.1.0"],"PathHashPairs":[{"Path":"/skins/foundation/js/1.foundation.min.js","Hash":"a152251b2cd890a58d6cf0dfa8609221"}]},{"Versions":["6.1.1","6.1.0"],"PathHashPairs":[{"Path":"/skins/foundation/js/2.cubecart.js","Hash":"3ae21d9de0745bb0b7e9faf5b01578ce"}]},{"Versions":["6.2.9","6.2.8","6.2.7","6.2.6","6.2.5","6.2.4","6.2.3","6.2.2","6.2.1","6.2.0","6.1.9","6.1.8","6.1.7","6.1.6","6.1.5","6.1.4","6.1.3","6.1.2","6.1.15","6.1.14","6.1.13","6.1.12","6.1.11","6.1.10","6.1.1"],"PathHashPairs":[{"Path":"/images/icons/prod_type_1.png","Hash":"5c167df22b84b90561ebc583af0971e9"}]},{"Versions":["6.2.9","6.2.8","6.2.7","6.2.6","6.2.5","6.2.4","6.2.3","6.2.2","6.2.1","6.2.0","6.1.9","6.1.8","6.1.7","6.1.6","6.1.5","6.1.4","6.1.3","6.1.2","6.1.15","6.1.14","6.1.13","6.1.12","6.1.11","6.1.10"],"PathHashPairs":[{"Path":"/js/plugins/jquery.chosen.js","Hash":"91d5b21be3297103e53ce06699f76e0e"}]},{"Versions":["6.2.5","6.2.4","6.2.3","6.2.2","6.2.1","6.2.0","6.1.9","6.1.8","6.1.7","6.1.6","6.1.5","6.1.15","6.1.14","6.1.13","6.1.12","6.1.11","6.1.10"],"PathHashPairs":[{"Path":"/js/plugins/jquery.filetree.js","Hash":"9aa836c703da52ba91c1a04e15cb2c8c"}]},{"Versions":["6.2.9","6.2.8","6.2.7","6.2.6","6.2.5","6.2.4","6.2.3","6.2.2","6.2.1","6.2.0","6.1.9","6.1.15","6.1.14","6.1.13","6.1.12","6.1.11","6.1.10"],"PathHashPairs":[{"Path":"/js/styles/images/ui-bg_glass_75_dadada_1x400.png","Hash":"efee44ffaf6515a83c1d025479b1e076"}]},{"Versions":["6.1.9","6.1.12","6.1.11","6.1.10"],"PathHashPairs":[{"Path":"/skins/foundation/css/cubecart.css","Hash":"7f788832472e286eb84a2a30fc17c5b3"}]},{"Versions":["6.2.9","6.2.8","6.2.7","6.2.6","6.2.5","6.2.4","6.2.3","6.2.2","6.2.1","6.1.9","6.1.15","6.1.14","6.1.13","6.1.12","6.1.11","6.1.10"],"PathHashPairs":[{"Path":"/skins/foundation/css/jquery.bxslider.css","Hash":"0782e3df0bb1d1ce5757c050064eec8f"}]},{"Versions":["6.1.9","6.1.8","6.1.7","6.1.6","6.1.5","6.1.4","6.1.3","6.1.2","6.1.15","6.1.14","6.1.13","6.1.12","6.1.11","6.1.10"],"PathHashPairs":[{"Path":"/skins/foundation/css/jquery.chosen.min.css","Hash":"dc0eda14532a74919f9374c5b2c61964"}]},{"Versions":["6.1.9","6.1.10"],"PathHashPairs":[{"Path":"/skins/foundation/js/2.cubecart.js","Hash":"3b526e7bce561855c0f6d56b2add672e"}]},{"Versions":["6.1.9","6.1.8","6.1.7","6.1.6","6.1.12","6.1.11","6.1.10"],"PathHashPairs":[{"Path":"/skins/foundation/js/3.cubecart.validate.js","Hash":"981fe3809319f86bb90a6e78601e2099"}]},{"Versions":["6.1.14","6.1.13","6.1.12","6.1.11"],"PathHashPairs":[{"Path":"/skins/foundation/js/2.cubecart.js","Hash":"c59653ddf528c0515ac761fc8fe1fc7f"}]},{"Versions":["6.1.13"],"PathHashPairs":[{"Path":"/skins/foundation/css/cubecart.css","Hash":"09836b3b2f80580fea9a804197f9bc6d"},{"Path":"/skins/foundation/js/3.cubecart.validate.js","Hash":"bc9c6ce6fd7aaec478fc5b04920fb89f"}]},{"Versions":["6.2.9","6.2.8","6.2.7","6.2.6","6.2.5","6.2.4","6.2.3","6.2.2","6.2.1","6.2.0","6.1.15","6.1.14"],"PathHashPairs":[{"Path":"/js/plugins/jquery.colorbox-min.js","Hash":"2f549896ba04317b11a5f773c03d7739"}]},{"Versions":["6.1.15","6.1.14"],"PathHashPairs":[{"Path":"/skins/foundation/css/cubecart.css","Hash":"06f6c4f841d04454d3a5f2f0f352089e"}]},{"Versions":["6.1.15"],"PathHashPairs":[{"Path":"/skins/foundation/js/2.cubecart.js","Hash":"4bda59ac13e2d476422fcba90a7274b2"},{"Path":"/skins/foundation/js/vendor/jquery.bxslider.min.js","Hash":"625c7df2ddeee578c4d4648daac53581"}]},{"Versions":["6.1.3","6.1.2"],"PathHashPairs":[{"Path":"/skins/foundation/js/2.cubecart.js","Hash":"4d4ea928d1090e9dcb51dfc28efb62dd"}]},{"Versions":["6.1.5","6.1.4","6.1.3","6.1.2"],"PathHashPairs":[{"Path":"/skins/foundation/js/3.cubecart.validate.js","Hash":"ef119b764142a2ba9fe2eb0cf18ee447"}]},{"Versions":["6.1.5","6.1.4"],"PathHashPairs":[{"Path":"/skins/foundation/css/cubecart.css","Hash":"57f4d67a8e3479854466196e6a52d0b5"}]},{"Versions":["6.1.6"],"PathHashPairs":[{"Path":"/skins/foundation/css/cubecart.css","Hash":"2dda5ee1c07bf5d6979a188f031affd4"}]},{"Versions":["6.1.8","6.1.7","6.1.6"],"PathHashPairs":[{"Path":"/skins/foundation/js/2.cubecart.js","Hash":"86381c76284d10b61004142101444ec3"}]},{"Versions":["6.1.8","6.1.7"],"PathHashPairs":[{"Path":"/skins/foundation/css/cubecart.css","Hash":"c19a791ac2c55fbcf51625654f086de4"}]},{"Versions":["6.2.0"],"PathHashPairs":[{"Path":"/skins/foundation/css/cubecart.css","Hash":"c7cebbc94d375e5e7cb8cbce2e39c214"},{"Path":"/skins/foundation/css/jquery.bxslider.css","Hash":"c77c6c30868cf33bd8043ae0b4eb02be"},{"Path":"/skins/foundation/js/2.cubecart.js","Hash":"4cc56140961fc82c29f598ea4040948c"}]},{"Versions":["6.2.9","6.2.8","6.2.7","6.2.6","6.2.5","6.2.4","6.2.3","6.2.2","6.2.1","6.2.0"],"PathHashPairs":[{"Path":"/skins/foundation/css/jquery.chosen.css","Hash":"d8fcb93d7b26a1689529eacb3b266085"}]},{"Versions":["6.2.6","6.2.5","6.2.4","6.2.3","6.2.2","6.2.1","6.2.0"],"PathHashPairs":[{"Path":"/skins/foundation/js/1.foundation.js","Hash":"5d2f1cd2358f87d44323f67a833b14de"}]},{"Versions":["6.2.5","6.2.4","6.2.3","6.2.2","6.2.1","6.2.0"],"PathHashPairs":[{"Path":"/skins/foundation/js/3.cubecart.validate.js","Hash":"682e3cf59351268edd8c47f9c6b83d8a"}]},{"Versions":["6.2.2","6.2.1"],"PathHashPairs":[{"Path":"/skins/foundation/css/cubecart.css","Hash":"fd64a8ff86116c598aeaa26028e4db09"}]},{"Versions":["6.2.9","6.2.8","6.2.7","6.2.6","6.2.5","6.2.4","6.2.3","6.2.2","6.2.1"],"PathHashPairs":[{"Path":"/skins/foundation/css/foundation.css","Hash":"d696803966d61f1036668899246b4df2"}]},{"Versions":["6.2.9","6.2.8","6.2.7","6.2.6","6.2.5","6.2.4","6.2.3"],"PathHashPairs":[{"Path":"/skins/foundation/css/cubecart.css","Hash":"1f149198226307f01f35e2f2556b75b3"}]},{"Versions":["6.2.5","6.2.4","6.2.3"],"PathHashPairs":[{"Path":"/skins/foundation/js/2.cubecart.js","Hash":"0d733a1fa4aac556094e0d451429e6be"}]},{"Versions":["6.2.9","6.2.8","6.2.7","6.2.6"],"PathHashPairs":[{"Path":"/js/plugins/jquery.filetree.js","Hash":"1063e64f945cd1647b1aaa7754730f75"}]},{"Versions":["6.2.8","6.2.7","6.2.6"],"PathHashPairs":[{"Path":"/skins/foundation/js/2.cubecart.js","Hash":"cc64143123bfaab324cb6c76df161b79"}]},{"Versions":["6.2.6"],"PathHashPairs":[{"Path":"/skins/foundation/js/3.cubecart.validate.js","Hash":"f1fbc209d5415992d7216066893cf273"}]},{"Versions":["6.2.9","6.2.8","6.2.7"],"PathHashPairs":[{"Path":"/skins/foundation/js/1.foundation.js","Hash":"6bd6fafd0009779bbf512aceb13b81ce"}]},{"Versions":["6.2.9"],"PathHashPairs":[{"Path":"/setup/styles/style.css","Hash":"b369c51ccf7f6fb3035814dcb147e162"},{"Path":"/skins/foundation/js/2.cubecart.js","Hash":"b385ccca81187e671d7ea0cec1fa2611"}]}]}