{"Name":"Logaholic","VersionNodes":[{"Versions":["Service_Provider_Edition(old)","Service_Provider_Edition","Self_Hosted_Edition(old)","Self_Hosted_Edition","Enterprise_Edition(old)","Enterprise_Edition"],"PathHashPairs":[{"Path":"/ReadMe.txt","Hash":"cd63f184a0d1eaf8e547a969d189ba98"}]},{"Versions":["Service_Provider_Edition","Self_Hosted_Edition","Enterprise_Edition"],"PathHashPairs":[{"Path":"/UPGRADE Instructions.txt","Hash":"d14775fe8b9e963657e3687a547a1e90"}]},{"Versions":["Self_Hosted_Edition(old)","Self_Hosted_Edition","Enterprise_Edition(old)","Enterprise_Edition"],"PathHashPairs":[{"Path":"/logaholic/License.txt","Hash":"0b270c55629579974c1a2387f946fbc4"}]},{"Versions":["Enterprise_Edition"],"PathHashPairs":[{"Path":"/logaholic/components/Subscriptions/subscriptions.css","Hash":"af221e5e03bc2621be09b031f103a338"}]},{"Versions":["Service_Provider_Edition(old)","Self_Hosted_Edition(old)","Enterprise_Edition(old)"],"PathHashPairs":[{"Path":"/UPGRADE Instructions.txt","Hash":"66a49465b665389dfbef120c85a121ea"}]},{"Versions":["Enterprise_Edition(old)"],"PathHashPairs":[{"Path":"/logaholic/revision.txt","Hash":"49de80b7cbcc4bd90008425a29c7318f"}]},{"Versions":["Service_Provider_Edition(old)","Self_Hosted_Edition(old)"],"PathHashPairs":[{"Path":"/logaholic/revision.txt","Hash":"e439166e69fe9b1fe3082a3e70e3a443"}]},{"Versions":["Service_Provider_Edition(old)","Service_Provider_Edition"],"PathHashPairs":[{"Path":"/logaholic/LicenseSPE.txt","Hash":"b442cabd6ead47d3616c65df74dc04ec"}]}]}