{"Name":"zencart","VersionNodes":[{"Versions":["1.5.6a","1.5.6","1.5.5f","1.5.5e","1.5.5d","1.5.5c","1.5.5b","1.5.5a","1.5.5","1.5.4","1.5.3"],"PathHashPairs":[{"Path":"/favicon.ico","Hash":"5febbca2a60333323525e78c1f78dc32"}]},{"Versions":["1.5.4","1.5.3"],"PathHashPairs":[{"Path":"/install.txt","Hash":"d30d3f1bce0aefb6c9b69fc6b295ee1e"}]},{"Versions":["1.5.3"],"PathHashPairs":[{"Path":"/README.md","Hash":"a908df7b3b2a8285a41d745443a7eccb"},{"Path":"/images/sooty.jpg","Hash":"97c4bf65adec5ae74de5ef1e440eadb5"}]},{"Versions":["1.5.5f","1.5.5e","1.5.5d","1.5.5c","1.5.5b","1.5.5a","1.5.5","1.5.4","1.5.3"],"PathHashPairs":[{"Path":"/images/banners/big-book-ad.gif","Hash":"80ddac609a76e3cfb7d6b44f47ad3d00"}]},{"Versions":["1.5.4"],"PathHashPairs":[{"Path":"/README.md","Hash":"fe9622c78fbf79e0850c9a0f3f328f0d"}]},{"Versions":["1.5.6a","1.5.6","1.5.5f","1.5.5e","1.5.5d","1.5.5c","1.5.5b","1.5.5a","1.5.5","1.5.4"],"PathHashPairs":[{"Path":"/images/sooty.jpg","Hash":"ac0c92edd87192ab485b8fa3cbcebec0"}]},{"Versions":["1.5.5f","1.5.5e","1.5.5d","1.5.5c","1.5.5b","1.5.5a","1.5.5"],"PathHashPairs":[{"Path":"/CONTRIBUTING.md","Hash":"7efd799de2e1521f96edd6ea70ba412c"}]},{"Versions":["1.5.5a","1.5.5"],"PathHashPairs":[{"Path":"/README.md","Hash":"dd73201fe5e7d9453c681be5ab4415bb"}]},{"Versions":["1.5.6a","1.5.6","1.5.5f","1.5.5e","1.5.5d","1.5.5c","1.5.5b","1.5.5a","1.5.5"],"PathHashPairs":[{"Path":"/email/email_common.css","Hash":"62cee9a200c1f00467fa03554cdbe9b7"}]},{"Versions":["1.5.5b"],"PathHashPairs":[{"Path":"/README.md","Hash":"dbcacc98c10ee0cca8110fa5f5786ce9"}]},{"Versions":["1.5.5c"],"PathHashPairs":[{"Path":"/README.md","Hash":"53ad8bfb288441b22b7bfcc0df9f25c5"}]},{"Versions":["1.5.5d"],"PathHashPairs":[{"Path":"/README.md","Hash":"a0149e7ba88892b8ca73d104a7ba06ae"}]},{"Versions":["1.5.5e"],"PathHashPairs":[{"Path":"/README.md","Hash":"7e219626bb1ca6cdbb0106b1eaadb7d4"}]},{"Versions":["1.5.5f"],"PathHashPairs":[{"Path":"/README.md","Hash":"28c15b7e003ece7ba98fcccb4eccec21"}]},{"Versions":["1.5.6a","1.5.6"],"PathHashPairs":[{"Path":"/install.txt","Hash":"d97e99713dc287ee4acee547ba6958cc"}]},{"Versions":["1.5.6"],"PathHashPairs":[{"Path":"/README.md","Hash":"13ac037aaca37118379a5b265f3c727f"}]},{"Versions":["1.5.6a"],"PathHashPairs":[{"Path":"/README.md","Hash":"81687031150e04c8c47a5fb06d9f3162"}]}]}